{
  "name": "a_new_home",
  "orderWeight": 50,
  "title": "Game",
  "subTitle": "A New Home",
  "description": "An interstellar ark with a thousand refugees has left Sol. You are tasked with finding a hospitable planet, one with an Earth-like climate. However, your resources are running low and your interstellar ark is falling apart.",
  "gamemodeKey": "a_new_home",
  "version": 12,
  "meta": "A New Home",
  "metaKeyValues": {},
  "created": "2019-03-28T16:25:53.614539-07:00",
  "modified": "2019-03-28T16:25:53.614539-07:00",
  "id": "a_new_home",
  "SaveType": "GamemodeInfo",
  "SiblingBehaviour": "All"
}